PyLineNotify/__init__.py
PyLineNotify/notifer.py
pylinenotify-1.2.1.dist-info/LICENSE.md
pylinenotify-1.2.1.dist-info/METADATA
pylinenotify-1.2.1.dist-info/WHEEL
pylinenotify-1.2.1.dist-info/top_level.txt
pylinenotify-1.2.1.dist-info/RECORD
