Metadata-Version: 2.1
Name: pylinenotify
Version: 1.2.1
Summary: using LineNotify more easily
Home-page: https://github.com/reud/PyLineNotify
Author: reud
Author-email: mail@reud.net
License: MIT
Project-URL: Bug Reports, https://github.com/reud/PyLineNotify/issues
Project-URL: Source, https://github.com/reud/PyLineNotify
Keywords: LINENotify
Platform: UNKNOWN
Classifier: License :: OSI Approved :: MIT License
Classifier: Programming Language :: Python :: 3.5
Classifier: Programming Language :: Python :: 3.6
Classifier: Programming Language :: Python :: 3.7
Requires-Dist: requests
